<?xml version="1.0" encoding="utf-8" standalone="yes"?>
<!--version="1.0" encoding="utf-8" standalone="yes"-->
<window>
	<id>2016</id>
	<defaultcontrol>4</defaultcontrol>
	<allowoverlay>control.isvisible(13371337)</allowoverlay>
	<animation effect="fade" time="250">WindowOpen</animation>
	<animation effect="fade" time="250">WindowClose</animation>
	<controls>
		<control>
			<type>image</type>
			<id>0</id>
			<posX>1000</posX>
			<posY>753</posY>
			<width>912</width>
			<height>325</height>
			<texture>bg_button2_focus.png</texture>
			<colordiffuse>f0ffffff</colordiffuse>
		</control>
		<control>
			<id>0</id>
			<type>image</type>
			<posX>1050</posX>
			<posY>795</posY>
			<width>810</width>
			<height>79</height>
			<texture>bg_facade4_line_nofocus.png</texture>
			<colordiffuse>77ffffff</colordiffuse>
		</control>
		<control>
			<description>Heading text label</description>
			<type>label</type>
			<id>3</id>
			<posX>1068</posX>
			<posY>807</posY>
			<label>181</label>
			<font>font22</font>
			<textcolor>FFFFFFFF</textcolor>
			<width>697</width>
		</control>
		<control>
			<description>OK button</description>
			<type>button</type>
			<id>4</id>
			<posX>1806</posX>
			<posY>822</posY>
			<width>39</width>
			<height>39</height>
			<label>-</label>
			<onleft>4</onleft>
			<onright>4</onright>
			<onup>4</onup>
			<ondown>4</ondown>
			<texture>-</texture>
			<textureFocus>button_close_focus.png</textureFocus>
			<textureNoFocus>button_close_nofocus.png</textureNoFocus>
		</control>
		<control>
			<description>logo</description>
			<type>image</type>
			<id>5</id>
			<posX>1695</posX>
			<posY>886</posY>
			<width>153</width>
			<height>115</height>
			<texture>#thumb</texture>
			<colordiffuse>FFFFFFFF</colordiffuse>
			<keepaspectratio>yes</keepaspectratio>
			<centered>yes</centered>
		</control>
		<control>
			<description>Thumb</description>
			<type>image</type>
			<id>0</id>
			<posX>1690</posX>
			<posY>880</posY>
			<width>163</width>
			<height>141</height>
			<texture>bg_tv_channel.png</texture>
			<!-- <visible>control.hasthumb(5)</visible> -->
			<visible>!string.equals(#thumb,)</visible>
		</control>
		<control>
			<description>textarea</description>
			<type>textbox</type>
			<id>6</id>
			<posX>1068</posX>
			<posY>879</posY>
			<width>586</width>
			<height>168</height>
			<spinPosX>3046</spinPosX>
			<spinPosY>961</spinPosY>
			<onleft>4</onleft>
			<onright>4</onright>
			<onup>4</onup>
			<ondown>4</ondown>
			<label>-</label>
			<textcolor>b0FFFFFF</textcolor>
		</control>
	</controls>
</window>