<?xml version="1.0" encoding="utf-8" standalone="yes"?>
<window>
	<id>4758</id>
	<defaultcontrol>13</defaultcontrol>
	<allowoverlay>control.isvisible(13371337)</allowoverlay>
	<define>#play.progressbar.percentage:#percentage</define>
	<define>#play.progressbar.currentplaytime:#currentplaytime</define>
	<define>#play.progressbar.currentremaining:#currentremaining</define>
	<controls>
		<!-- these elements need condition visibility for OSD IS VISIBLE -->
		
		<control>
			<description>background up</description>
			<id>300</id>
			<type>image</type>
			<posX>149</posX>
			<posY>580</posY>
			<width>982</width>
			<height>136</height>
			<texture>bg_osd_small_top.png</texture>
			<animation effect="fade" time="100">visible</animation>
			<visible>[player.rewinding|control.isvisible(10)|control.isvisible(11)|control.isvisible(12)|player.forwarding|player.paused]+!window.isosdvisible</visible>
		</control>
		<control>
			<description>progressbar background</description>
			<id>999</id>
			<type>image</type>
			<posX>180</posX>
			<posY>653</posY>
			<height>29</height>
			<width>920</width>
			<texture>bg_osd_small_progress_background.png</texture>
			<animation effect="fade" time="100">visible</animation>
			<visible>[player.paused|player.rewinding|player.forwarding|control.isvisible(10)|control.isvisible(11)|control.isvisible(12)]+!window.isosdvisible</visible>
		</control>
		<control>
			<description>Movie Name</description>
			<id>36</id>
			<type>fadelabel</type>
			<width>740</width>
			<posX>200</posX>
			<posY>618</posY>
			<font>font18</font>
			<label>#Play.Current.Title</label>
			<textcolor>white</textcolor>
			<textalign>left</textalign>
			<wrapString> : : : </wrapString>
			<animation effect="fade" time="100">visible</animation>
			<visible>[player.rewinding|control.isvisible(10)|control.isvisible(11)|control.isvisible(12)|player.forwarding|player.paused]+!window.isosdvisible</visible>
		</control>

		<!-- <control>
			<description>progress bar background</description>
			<type>image</type>
			<posX>-10</posX>
			<posY>685</posY>
			<width>1300</width>
			<height>36</height>
			<texture>osd_progress_background.png</texture>
			<visible>!window.isosdvisible+[player.paused|player.rewinding|player.forwarding|control.isvisible(10)|control.isvisible(11)|control.isvisible(12)]</visible>
			<animation effect="fade" time="100">visible</animation>
		</control>
		<control>
			<description>progress bar</description>
			<type>progress</type>
			<id>1</id>
			<posX>-12</posX>
			<posY>-685</posY>
			<width>1304</width>
			<height>36</height>
			<label>#play.progressbar.percentage</label>
			<visible>[window.isosdvisible|player.paused|player.rewinding|player.forwarding|control.isvisible(10)]+!window.isvisible(4758)</visible>
			<animation effect="fade" time="100">visible</animation>
		</control> -->
		<control>
			<description>TV Progress Bar</description>
			<type>tvprogress</type>
			<id>101</id>
			<posX>180</posX>
			<posY>653</posY>
			<height>29</height>
			<width>897</width>
			<toptexture>-</toptexture>   
			<TextureOffsetY>18</TextureOffsetY>
			<bottomtexture>-</bottomtexture>
			<texturetick>-</texturetick>
			<lefttexture>osd_small_progress_left_blue.png</lefttexture>
			<midtexture>-</midtexture>
			<righttexture>-</righttexture>
			<logotexture>-</logotexture>
			<fillbackgroundtexture>-</fillbackgroundtexture>
			<fillbgxoff>-3</fillbgxoff>
			<fillbgyoff>0</fillbgyoff>
			<filltexture1>osd_small_progress_mid_blue.png</filltexture1>
			<filltexture2>osd_small_progress_mid_red.png</filltexture2>
			<filltexture3>osd_small_progress_mid_green.png</filltexture3>
			<fillheight>29</fillheight>
			<label>#percentage</label>
			<label1>#percentage</label1>
			<label2>#TV.Record.percent3</label2>
			<font>font13</font>
			<textcolor>FF000000</textcolor>
			<animation effect="fade" time="100">visible</animation>
		</control>
		<control>
			<description>Start Time Info</description>
			<id>999</id>
			<type>label</type>
			<posX>200</posX>
			<posY>654</posY>
			<label>#play.progressbar.currentplaytime</label>
			<align>left</align>
			<font>font14</font>
			<textcolor>white</textcolor>
			<visible>window.isosdvisible|player.paused|player.rewinding|player.forwarding|control.isvisible(10)|control.isvisible(11)|control.isvisible(12)</visible>
			<animation effect="fade" time="100">visible</animation>
			<shadowAngle>315</shadowAngle>
			<shadowDistance>1</shadowDistance>
			<shadowColor>FF000000</shadowColor>
		</control>
		<control>
			<description>End Time Info</description>
			<id>999</id>
			<type>label</type>
			<posX>1080</posX>
			<posY>654</posY>
			<label>#play.progressbar.currentremaining</label>
			<align>right</align>
			<font>font14</font>
			<textcolor>white</textcolor>
			<visible>window.isosdvisible|player.paused|player.rewinding|player.forwarding|control.isvisible(10)|control.isvisible(11)|control.isvisible(12)</visible>
			<animation effect="fade" time="100">visible</animation>
			<shadowAngle>315</shadowAngle>
			<shadowDistance>1</shadowDistance>
			<shadowColor>FF000000</shadowColor>
		</control>

		<control>
			<description>Time</description>
			<type>fadelabel</type>
			<id>0</id>
			<posX>1058</posX>
			<posY>625</posY>
			<width>300</width>
			<font>font12</font>
			<align>right</align>
			<label>#time</label>
			<textcolor>47ffffff</textcolor>
			<visible>[player.paused|player.rewinding|player.forwarding|control.isvisible(10)|control.isvisible(11)|control.isvisible(12)]+!window.isosdvisible</visible>
			<animation effect="fade" time="100">visiblechange</animation>
			<animation effect="fade" time="100">windowopen</animation>
		</control>
		<control>
			<description>time logo</description>
			<type>image</type>
			<id>0</id>
			<posX>1060</posX>
			<posY>625</posY>
			<height>22</height>
			<width>22</width>
			<texture>time.png</texture>
			<colordiffuse>79ffffff</colordiffuse>
			<visible>[player.paused|player.rewinding|player.forwarding|control.isvisible(10)|control.isvisible(11)|control.isvisible(12)]+!window.isosdvisible</visible>
			<animation effect="fade" time="100">visiblechange</animation>
			<animation effect="fade" time="100">windowopen</animation>
		</control>
		
		<control>
			<type>image</type>
			<description>Time icon</description>
			<id>999</id>
			<posX>654</posX>
			<posY>657</posY>
			<height>22</height>
			<width>22</width>
			<texture>time.png</texture>
			<colordiffuse>ffffffff</colordiffuse>
			<visible>![player.rewinding|control.isvisible(10)|control.isvisible(11)|control.isvisible(12)|player.forwarding|player.paused]+window.isosdvisible</visible>
			<animation effect="fade" time="100">visible</animation>
		</control>

		<control>
			<type>label</type>
			<description>Time</description>
			<id>999</id>
			<posX>652</posX>
			<posY>657</posY>
			<font>font12</font>
			<align>right</align>
			<label>#time</label>
			<textcolor>ffffffff</textcolor>
			<visible>![player.rewinding|control.isvisible(10)|control.isvisible(11)|control.isvisible(12)|player.forwarding|player.paused]+window.isosdvisible</visible>
			<animation effect="fade" time="100">visible</animation>
			<shadowAngle>315</shadowAngle>
			<shadowDistance>1</shadowDistance>
			<shadowColor>FF000000</shadowColor>
		</control>
		<!-- END OF these elements need condition visibility for OSD IS VISIBLE -->
		<control>
			<description>pause image</description>
			<id>999</id>
			<type>image</type>
			<posX>580</posX>
			<posY>654</posY>
			<width>120</width>
			<height>27</height>
			<visible>player.paused+!control.isvisible(10)|control.isvisible(11)|control.isvisible(12)</visible>
			<texture>video_paused.png</texture>
			<colorkey>0</colorkey>
			<colordiffuse>White</colordiffuse>
			<animation effect="fade" time="100">visible</animation>
		</control>
		<control>
			<description>2x image</description>
			<type>image</type>
			<posX>580</posX>
			<posY>654</posY>
			<width>119</width>
			<height>28</height>
			<visible>player.forwarding2x+!control.isvisible(10)|control.isvisible(11)|control.isvisible(12)</visible>
			<texture>video+2x.png</texture>
			<colorkey>0</colorkey>
			<colordiffuse>White</colordiffuse>
			<animation effect="fade" time="100">visible</animation>
		</control>
		<control>
			<description>4x image</description>
			<type>image</type>
			<posX>580</posX>
			<posY>654</posY>
			<width>119</width>
			<height>28</height>
			<visible>player.forwarding4x+!control.isvisible(10)|control.isvisible(11)|control.isvisible(12)</visible>
			<texture>video+4x.png</texture>
			<colorkey>0</colorkey>
			<colordiffuse>White</colordiffuse>
			<animation effect="fade" time="100">visible</animation>
		</control>
		<control>
			<description>8x image</description>
			<type>image</type>
			<posX>580</posX>
			<posY>654</posY>
			<width>119</width>
			<height>28</height>
			<visible>player.forwarding8x+!control.isvisible(10)|control.isvisible(11)|control.isvisible(12)</visible>
			<texture>video+8x.png</texture>
			<colorkey>0</colorkey>
			<colordiffuse>White</colordiffuse>
			<animation effect="fade" time="100">visible</animation>
		</control>
		<control>
			<description>16x image</description>
			<type>image</type>
			<posX>580</posX>
			<posY>654</posY>
			<width>119</width>
			<height>28</height>
			<visible>player.forwarding16x+!control.isvisible(10)|control.isvisible(11)|control.isvisible(12)</visible>
			<texture>video+16x.png</texture>
			<colorkey>0</colorkey>
			<colordiffuse>White</colordiffuse>
			<animation effect="fade" time="100">visible</animation>
		</control>
		<control>
			<description>32x image</description>
			<type>image</type>
			<posX>580</posX>
			<posY>654</posY>
			<width>119</width>
			<height>28</height>
			<visible>player.forwarding32x+!control.isvisible(10)|control.isvisible(11)|control.isvisible(12)</visible>
			<texture>video+32x.png</texture>
			<colorkey>0</colorkey>
			<colordiffuse>White</colordiffuse>
			<animation effect="fade" time="100">visible</animation>
		</control>
		<control>
			<description>- 2x image</description>
			<type>image</type>
			<id>23</id>
			<posX>580</posX>
			<posY>654</posY>
			<width>119</width>
			<height>28</height>
			<visible>player.rewinding2x+!control.isvisible(10)|control.isvisible(11)|control.isvisible(12)</visible>
			<texture>video-2x.png</texture>
			<colorkey>0</colorkey>
			<colordiffuse>White</colordiffuse>
			<animation effect="fade" time="100">visible</animation>
		</control>
		<control>
			<description>- 4x image</description>
			<type>image</type>
			<id>24</id>
			<posX>580</posX>
			<posY>654</posY>
			<width>119</width>
			<height>28</height>
			<visible>player.rewinding4x+!control.isvisible(10)|control.isvisible(11)|control.isvisible(12)</visible>
			<texture>video-4x.png</texture>
			<colorkey>0</colorkey>
			<colordiffuse>White</colordiffuse>
			<animation effect="fade" time="100">visible</animation>
		</control>
		<control>
			<description>- 8x image</description>
			<type>image</type>
			<id>25</id>
			<posX>580</posX>
			<posY>654</posY>
			<width>119</width>
			<height>28</height>
			<visible>player.rewinding8x+!control.isvisible(10)|control.isvisible(11)|control.isvisible(12)</visible>
			<texture>video-8x.png</texture>
			<colorkey>0</colorkey>
			<colordiffuse>White</colordiffuse>
			<animation effect="fade" time="100">visible</animation>
		</control>
		<control>
			<description>- 16x image</description>
			<type>image</type>
			<id>26</id>
			<posX>580</posX>
			<posY>654</posY>
			<width>119</width>
			<height>28</height>
			<visible>player.rewinding16x+!control.isvisible(10)|control.isvisible(11)|control.isvisible(12)</visible>
			<texture>video-16x.png</texture>
			<colorkey>0</colorkey>
			<colordiffuse>White</colordiffuse>
			<animation effect="fade" time="100">visible</animation>
		</control>
		<control>
			<description>- 32x image</description>
			<type>image</type>
			<id>27</id>
			<posX>580</posX>
			<posY>654</posY>
			<width>119</width>
			<height>28</height>
			<visible>player.rewinding32x+!control.isvisible(10)|control.isvisible(11)|control.isvisible(12)</visible>
			<texture>video-32x.png</texture>
			<colorkey>0</colorkey>
			<colordiffuse>White</colordiffuse>
			<animation effect="fade" time="100">visible</animation>
		</control>

		<import>common.play.fullscreen.xml</import>
		<import>common.play.fullscreen.volume.xml</import>

		<control>
			<type>image</type>
			<id>502</id>
			<posX>576</posX>
			<posY>300</posY>
			<height>128</height>
			<width>128</width>
			<texture>video.action.forbidden.png</texture>
			<colorkey>0</colorkey>
			<colordiffuse>White</colordiffuse>
			<visible>no</visible>
			<animation effect="fade" time="100">visiblechange</animation>
		</control>
	</controls>
</window>
